amebo/__init__.py
amebo/amebo.sh
amebo/amebo_readers.py
amebo/amebo_writers.py
amebo/aproko.py
amebo/constants/__init__.py
amebo/constants/literals.py
amebo/constants/scripts.py
amebo/controllers/__init__.py
amebo/controllers/actions.py
amebo/controllers/applications.py
amebo/controllers/events.py
amebo/controllers/gists.py
amebo/controllers/subscriptions.py
amebo/controllers/xui.py
amebo/database/mysql.py
amebo/database/pg.py
amebo/database/sqlite.py
amebo/decorators/__init__.py
amebo/decorators/formatters.py
amebo/decorators/providers.py
amebo/decorators/security.py
amebo/dist/amebo-0.1.1-py3-none-any.whl
amebo/dist/amebo-0.1.1.tar.gz
amebo/dist/amebo-0.1.2-py3-none-any.whl
amebo/dist/amebo-0.1.2.tar.gz
amebo/dist/amebo-0.2.0-py3-none-any.whl
amebo/dist/amebo-0.2.0.tar.gz
amebo/dist/amebo-0.3.0-py3-none-any.whl
amebo/dist/amebo-0.3.0.tar.gz
amebo/engines.py
amebo/entities.py
amebo/handlers.py
amebo/libs/__init__.py
amebo/libs/decorators.py
amebo/main.py
amebo/middleware.py
amebo/middlewares/__init__.py
amebo/middlewares/database.py
amebo/middlewares/security.py
amebo/middlewares/setup.py
amebo/models/actions.py
amebo/models/applications.py
amebo/models/events.py
amebo/models/subscriptions.py
amebo/public/all.css
amebo/public/alpine.min.js
amebo/public/amebo.webp
amebo/public/bulma.min.css
amebo/public/heaven.css
amebo/public/icons/add.svg
amebo/public/icons/bulb.svg
amebo/public/icons/ear.svg
amebo/public/icons/eye.svg
amebo/public/icons/flash-outline.svg
amebo/public/icons/hardware-chip.svg
amebo/public/icons/leaf-outline.svg
amebo/public/icons/megaphone.svg
amebo/public/icons/neye.svg
amebo/public/icons/search.svg
amebo/public/icons/send.svg
amebo/public/logo.svg
amebo/public/toastify.js
amebo/public/toastify.min.css
amebo/router.py
amebo/templates/404.html
amebo/templates/abase.axml
amebo/templates/actions.axml
amebo/templates/actions.html
amebo/templates/applications.html
amebo/templates/events.html
amebo/templates/functions.axml
amebo/templates/gists.html
amebo-0.6.0.dist-info/METADATA
amebo-0.6.0.dist-info/WHEEL
amebo-0.6.0.dist-info/entry_points.txt
amebo-0.6.0.dist-info/RECORD
