Metadata-Version: 2.4
Name: amebo
Version: 0.6.0
Summary: HTTP Event Notifications Server - A lightweight, schema-driven event broadcasting system for microservices and distributed applications
License: MIT
Keywords: event-driven,microservices,webhooks,pubsub,notifications
Author: Raymond Ortserga
Author-email: codesage@live.com
Requires-Python: >=3.8,<4.0
Classifier: Development Status :: 5 - Production/Stable
Classifier: Intended Audience :: Developers
Classifier: License :: OSI Approved :: MIT License
Classifier: Natural Language :: English
Classifier: Programming Language :: Python
Classifier: Programming Language :: Python :: 3
Classifier: Programming Language :: Python :: 3.8
Classifier: Programming Language :: Python :: 3.9
Classifier: Programming Language :: Python :: 3.10
Classifier: Programming Language :: Python :: 3.11
Classifier: Programming Language :: Python :: 3.12
Classifier: Programming Language :: Python :: 3.13
Classifier: Programming Language :: Python :: 3.14
Classifier: Topic :: Internet :: WWW/HTTP :: HTTP Servers
Classifier: Topic :: Software Development :: Libraries :: Python Modules
Classifier: Topic :: System :: Distributed Computing
Requires-Dist: asyncpg (>=0.30.0)
Requires-Dist: bcrypt (>=4.2.0)
Requires-Dist: fastjsonschema (>=2.19.1)
Requires-Dist: heaven (>=0.4.1)
Requires-Dist: httpx (>=0.27.0)
Requires-Dist: jinja2 (>=3.1.2)
Requires-Dist: orjson (>=3.8.5)
Requires-Dist: pydantic (>=2.0.0)
Requires-Dist: pyjwt (>=2.0.0)
Requires-Dist: python-dotenv (>=1.0.0)
Requires-Dist: redis (>=5.0.0)
Requires-Dist: uvicorn (>=0.20.0)
Project-URL: Bug Reports, https://github.com/rayattack/amebo/issues
Project-URL: Documentation, https://rayattack.github.io/amebo/
Project-URL: Docker Hub, https://hub.docker.com/r/rayattack/amebo
Project-URL: Homepage, https://github.com/rayattack/amebo
Project-URL: Repository, https://github.com/rayattack/amebo
